LICENSE.txt
MANIFEST.in
README.md
RELEASE-VERSION
setup.py
version.py
yakonfig/__init__.py
yakonfig/cmd.py
yakonfig/configurable.py
yakonfig/exceptions.py
yakonfig/factory.py
yakonfig/merge.py
yakonfig/toplevel.py
yakonfig/yakonfig.py
yakonfig.egg-info/PKG-INFO
yakonfig.egg-info/SOURCES.txt
yakonfig.egg-info/dependency_links.txt
yakonfig.egg-info/requires.txt
yakonfig.egg-info/top_level.txt
yakonfig/tests/__init__.py
yakonfig/tests/configurable_module.py
yakonfig/tests/test_configurable.py
yakonfig/tests/test_dump_config.py
yakonfig/tests/test_factory.py
yakonfig/tests/test_merge.py
yakonfig/tests/test_yakonfig.py