Metadata-Version: 1.1
Name: yakonfig
Version: 0.7.4
Summary: load a configuration dictionary for a large application
Home-page: http://github.com/diffeo/yakonfig
Author: Diffeo, Inc.
Author-email: support@diffeo.com
License: The MIT License (MIT)
